tokopedia_api_wrapper/__init__.py
tokopedia_api_wrapper/__version__.py
tokopedia_api_wrapper/constants.py
tokopedia_api_wrapper/tokopedia.py
tokopedia_api_wrapper/schemas/__init__.py
tokopedia_api_wrapper/schemas/product_schema.py
tokopedia_api_wrapper/schemas/response_schema.py
tokopedia_api_wrapper/utils/__init__.py
tokopedia_api_wrapper/utils/faker.py
tokopedia_api_wrapper/utils/transform.py
tokopedia_api_wrapper-0.0.2.dist-info/licenses/LICENSE
tokopedia_api_wrapper-0.0.2.dist-info/METADATA
tokopedia_api_wrapper-0.0.2.dist-info/WHEEL
tokopedia_api_wrapper-0.0.2.dist-info/top_level.txt
tokopedia_api_wrapper-0.0.2.dist-info/RECORD
